{
    "_id" : ObjectId("5e25e5550fb1e674472d7589"),
    "session_id" : "123456",
    "products" : [ 
        {
            "id" : ObjectId("5e207dbe899369e28ffaf86a"),
            "count" : 1
        }, 
        {
            "id" : ObjectId("5e207dc3899369e28ffaf872"),
            "count" : 3
        }
    ],
    "total_price" : 32,
    "last_modified" : {
        "date" : "20/01/2020",
        "time" : "15:30"
    }
}

{
    "_id" : ObjectId("5e25e7440fb1e674472d77b8"),
    "session_id" : "123457",
    "products" : [ 
        {
            "id" : ObjectId("5e207dbe899369e28ffaf86a"),
            "count" : 2
        }
    ],
    "total_price" : 22,
    "last_modified" : {
        "date" : "22/01/2020",
        "time" : "11:48"
    }
}